<?xml version = '1.0' encoding = 'UTF-8'?>
<FKIndexAssociation class="oracle.dbtools.crest.model.design.relational.FKIndexAssociation" directorySegmentName="seg_0" id="2B274851-2311-601B-635B-AAC4A092BD32" containerWithKeyObject="FD1B2322-9502-3ADF-F961-4A601737B67A" localFKIndex="EFB85110-0923-F9FA-F147-E0C9EA2CFD7E" name="PREF_KANAL_ADRESSE_ADVIS_ID_FK">
<sourceConnName>AogD_FKT03_ELpeu4muKQp4</sourceConnName>
<sourceObjSchema>AOGD</sourceObjSchema>
<sourceObjName>PREF_KANAL_ADRESSE_ADVIS_ID_FK</sourceObjName>
<createdBy>tnl</createdBy>
<createdTime>2020-06-03 12:16:10 UTC</createdTime>
<ownerDesignName>aogd_tb</ownerDesignName>
<referredTableLongName>AOGD.KANAL_ADRESSE</referredTableLongName>
<deleteRule>NO ACTION</deleteRule>
<referredTableID>129FD9F2-F89B-9A4A-751E-61C259008E59</referredTableID>
<keyObject>A9E2027E-5424-0960-720A-BA3C055A0CAA</keyObject>
<referredKeyID>A9E2027E-5424-0960-720A-BA3C055A0CAA</referredKeyID>
<mandatory>false</mandatory>
<refColNames>KANAL_ADRESSE_ID</refColNames>
<transferable>true</transferable>
<rely>false</rely>
<columnDependencyConstraintGenerateInDDL>true</columnDependencyConstraintGenerateInDDL>
</FKIndexAssociation>